setup.cfg
setup.py
device_info/__init__.py
device_info/device_info.py
device_info.egg-info/PKG-INFO
device_info.egg-info/SOURCES.txt
device_info.egg-info/dependency_links.txt
device_info.egg-info/not-zip-safe
device_info.egg-info/top_level.txt